voice_processor/__init__.py
voice_processor-0.0.8.dist-info/METADATA
voice_processor-0.0.8.dist-info/WHEEL
voice_processor-0.0.8.dist-info/top_level.txt
voice_processor-0.0.8.dist-info/RECORD
