Metadata-Version: 2.4
Name: voice-processor
Version: 0.0.8
Summary: A Python package for voice recognition, text-to-speech, and continuous voice listening
Author: mrfidal
Author-email: mrfidal@proton.me
Classifier: Programming Language :: Python :: 3
Classifier: Operating System :: OS Independent
Requires-Python: >=3.8
Requires-Dist: SpeechRecognition>=3.8.1
Requires-Dist: gTTS>=2.3.0
Requires-Dist: playsound>=1.3.0
Requires-Dist: PyAudio>=0.2.13
Dynamic: author
Dynamic: author-email
Dynamic: classifier
Dynamic: description
Dynamic: description-content-type
Dynamic: requires-dist
Dynamic: requires-python
Dynamic: summary
